{
	"configurations" : 
	[
		{
			"directories" : 
			[
				{
					"build" : ".",
					"jsonFile" : "directory-.-Debug-d0094a50bb2071803777.json",
					"minimumCMakeVersion" : 
					{
						"string" : "3.29"
					},
					"projectIndex" : 0,
					"source" : ".",
					"targetIndexes" : 
					[
						0
					]
				}
			],
			"name" : "Debug",
			"projects" : 
			[
				{
					"directoryIndexes" : 
					[
						0
					],
					"name" : "dvimaciaimasyvai",
					"targetIndexes" : 
					[
						0
					]
				}
			],
			"targets" : 
			[
				{
					"directoryIndex" : 0,
					"id" : "dvimaciaimasyvai::@6890427a1f51a3e7e1df",
					"jsonFile" : "target-dvimaciaimasyvai-Debug-c56d5b230f56d937d773.json",
					"name" : "dvimaciaimasyvai",
					"projectIndex" : 0
				}
			]
		}
	],
	"kind" : "codemodel",
	"paths" : 
	{
		"build" : "C:/Users/s062265/Desktop/strukturinis_programavimas/dvimaciaimasyvai/cmake-build-debug",
		"source" : "C:/Users/s062265/Desktop/strukturinis_programavimas/dvimaciaimasyvai"
	},
	"version" : 
	{
		"major" : 2,
		"minor" : 7
	}
}
